firebase/__init__.py
firebase/_custom_requests.py
firebase/_exception.py
firebase/_service_account_credentials.py
firebase/exceptions.py
firebase/auth/__init__.py
firebase/auth/oauth_flow.py
firebase/database/__init__.py
firebase/database/_custom_sse_client.py
firebase/database/_db_convert.py
firebase/database/_keep_auth_session.py
firebase/firestore/__init__.py
firebase/firestore/_utils.py
firebase/storage/__init__.py
async_firebase_rest_api-2.2.0.dist-info/LICENSE
async_firebase_rest_api-2.2.0.dist-info/WHEEL
async_firebase_rest_api-2.2.0.dist-info/METADATA
async_firebase_rest_api-2.2.0.dist-info/RECORD
