Metadata-Version: 2.1
Name: async-firebase-rest-api
Version: 2.2.0
Summary: An async python wrapper for Google's Firebase REST API's.
Keywords: firebase,firebase-auth,firebase-database,firebase-firestore,firebase-realtime-database,firebase-storage
Author-email: Asif Arman Rahman <asifarmanrahman@gmail.com>, Matias Kotlik <mdkotlik@gmail.com>
Requires-Python: >=3.11
Classifier: Development Status :: 5 - Production/Stable
Classifier: Intended Audience :: Developers
Classifier: License :: OSI Approved :: MIT License
Classifier: Natural Language :: English
Classifier: Operating System :: OS Independent
Classifier: Programming Language :: Python
Classifier: Programming Language :: Python :: 3
Classifier: Programming Language :: Python :: 3.11
Classifier: Topic :: Software Development :: Libraries :: Python Modules
Requires-Dist: google-auth>=2.9.1
Requires-Dist: google-cloud-firestore>=2.5.3
Requires-Dist: google-cloud-storage>=2.0.0
Requires-Dist: pkce>=1.0.0
Requires-Dist: python_jwt>=3.3.2
Requires-Dist: requests>=2.27.1
Requires-Dist: six>=1.16.0
Requires-Dist: httpx>=0.27.0
Requires-Dist: httpx-sse>=0.4.0
Requires-Dist: stamina>=24.2.0
Requires-Dist: Sphinx>=5.0.2 ; extra == "docs"
Requires-Dist: sphinx-rtd-theme>=1.0.0 ; extra == "docs"
Requires-Dist: sphinx_design>=0.2.0 ; extra == "docs"
Requires-Dist: toml>=0.10.2 ; extra == "docs"
Requires-Dist: flit>=3.7.1 ; extra == "tests"
Requires-Dist: pytest>=7.1.2 ; extra == "tests"
Requires-Dist: pytest-cov>=3.0.0 ; extra == "tests"
Requires-Dist: python-decouple>=3.6 ; extra == "tests"
Requires-Dist: pytest-asyncio>=0.23.6 ; extra == "tests"
Project-URL: Documentation, https://async-firebase-rest-api.readthedocs.io/
Project-URL: Source, https://github.com/matiaskotlik/async-firebase-rest-api
Provides-Extra: docs
Provides-Extra: tests
